still_rm/__init__.py
still_rm/__main__.py
still_rm-1.0.0.dist-info/METADATA
still_rm-1.0.0.dist-info/WHEEL
still_rm-1.0.0.dist-info/entry_points.txt
still_rm-1.0.0.dist-info/top_level.txt
still_rm-1.0.0.dist-info/RECORD
