Metadata-Version: 2.1
Name: still-rm
Version: 1.0.0
Summary: A utility for removing still frames from video files.
Home-page: https://github.com/joy2fun/still-rm
Author: Chiao
Author-email: php@html.js.cn
License: UNKNOWN
Platform: UNKNOWN
Requires-Dist: opencv-python (>=4.0)
Requires-Dist: ffmpeg-python (>=0.1)
